censusviz/__init__.py
censusviz/censusviz.py
censusviz-0.1.12.dist-info/LICENSE
censusviz-0.1.12.dist-info/WHEEL
censusviz-0.1.12.dist-info/METADATA
censusviz-0.1.12.dist-info/RECORD
