Metadata-Version: 2.1
Name: censusviz
Version: 0.1.12
Summary: A Python package to make it easier to visualize Census data.
Home-page: https://github.com/elliotttrio/censusviz
License: MIT
Author: Elliott
Author-email: eat2153@columbia.edu
Requires-Python: >=3.6,<4.0
Classifier: License :: OSI Approved :: MIT License
Classifier: Programming Language :: Python :: 3
Classifier: Programming Language :: Python :: 3.6
Classifier: Programming Language :: Python :: 3.7
Classifier: Programming Language :: Python :: 3.8
Requires-Dist: descartes
Requires-Dist: geopandas
Requires-Dist: lxml
Requires-Dist: matplotlib
Requires-Dist: pandas
Requires-Dist: requests
Project-URL: Documentation, https://github.com/elliotttrio/censusviz/blob/main/README.md
Project-URL: Repository, https://github.com/elliotttrio/censusviz
